single_cycle_MIPS/src/im.v
module im_1k(addr, dout) ;
    input   [9:0]  addr ;  // address bus
    output  [31:0]  dout ;  // 32-bit memory output
    reg     [7:0]  im[1023:0] ;
    assign dout={im[addr[9:0]],im[addr[9:0]+1],im[addr[9:0]+2],im[addr[9:0]+3]};
endmodule

single_cycle_MIPS/src/ext32.v
module ext32(input [15:0]imm, input [1:0]extop, input [31:0]b, input b_sel, output [31:0]alu_b);
    reg[31:0]imm32;

    assign alu_b=(b_sel)?imm32:b;

    always@(imm or extop)
    case(extop)
        2'b00:
            imm32={{16'b0},imm};
        2'b01:
            imm32={{16{imm[15]}},imm};
        2'b10:
            imm32={imm,{16'b0}};
        default:
            imm32=0;
    endcase
endmodule

single_cycle_MIPS/src/controller.v
module controller(input[31:0] din, output[4:0]rd, output[4:0]rs, output[4:0]rt, output[5:0]funct, output[5:0]opcode, output[15:0]imm);
    assign funct=din[5:0];
    assign opcode=din[31:26];
    assign rd=din[15:11];
    assign rs=din[25:21];
    assign rt=din[20:16];
    assign imm=din[15:0];
endmodule

single_cycle_MIPS/src/ifu.v
module ifu(input clk,input reset, input j_sel,input jr_sel,input npc_sel,input zero , input [31:0]jr,output reg [31:0]pc,output  [31:0]  dout);
    wire [31:0]npc,t4,t3,t2,t1,t0,extout,temp,j;
    wire [15:0]imm;
    reg     [7:0]  im[1023:0] ;

    assign imm=dout[15:0];
    assign temp={{16{imm[15]}},imm};
    assign extout=temp<<2;//计算偏移量

    assign j={pc[31:28],dout[25:0],2'b0};//计算目标地址

    assign dout={im[pc[9:0]],im[pc[9:0]+1],im[pc[9:0]+2],im[pc[9:0]+3]};
    
    always @(posedge clk , posedge reset) begin
        if(reset)
            pc<=32'h0000_3000;
        else
            pc<=npc;
    end

    assign npc=(jr_sel)?jr:t3;//寄存器跳转
    assign t3=(j_sel)?j:t2;//跳转指令
    assign t2=(npc_sel&&zero)?t1:t0;//条件跳转
    assign t0=pc+4;//顺序执行
    assign t1=t0+extout;//条件分支
endmodule

single_cycle_MIPS/src/gpr.v
module gpr(input [4:0]rs,  input [4:0]rt, input[4:0]rd, input [31:0]din,input flag_sel,input flag,input [31:0] pc,input clk,input rst,input jal_sel,input jr_sel,input regwr,output [31:0]a, output [31:0]b,input addi_sel);
    reg [31:0]t[31:0];
    integer i;
   
    assign a=(jr_sel)?t[31]:t[rs];
    assign b=t[rt];

    always @(posedge clk or posedge rst) begin
        if(rst)
            for(i=0;i<32;i=i+1)
                t[i]<=0;
        else
            if(regwr) begin
                t[28] = 32'h0000_1800;
                t[29] = 32'h0000_2ffc;
                
                if(jal_sel)
                    t[31]<=pc+4;

                if(flag_sel && flag) // addi overflow
                    t[30][0]<=flag;

                if (addi_sel && (rt != 0) && (flag == 0)) // addi write
                    t[rt] <= din; 

                else if (rd != 0 && addi_sel == 0) // other write
                    t[rd] <= din;
            end
    end
endmodule

single_cycle_MIPS/src/dm.v
module dm_1k(addr, din, we, clk, dout) ;
    input   [9:0]  addr ;
    input   [31:0]  din ;
    input           we ;    // memory write enable
    input           clk ;
    output  [31:0]  dout ;
    reg     [7:0]  dm[1023:0] ;//1024 bytes
    integer i;
    
    initial begin
        for (i = 0;i < 1024;i = i+1)
            dm[i] = 8'b0;
    end

    always @ (posedge clk) begin
        if(we) begin
            dm[addr[9:2]]<=din[7:0];
            dm[addr[9:2]+1]<=din[15:8];
            dm[addr[9:2]+2]<=din[23:16];
            dm[addr[9:2]+3]<=din[31:24];
        end
    end
    assign dout={dm[addr[9:2]+3],dm[addr[9:2]+2],dm[addr[9:2]+1],dm[addr[9:2]]};
endmodule

single_cycle_MIPS/src/controllersel.v
module controllersel(rt,opcode,funct,aluop,regwr,extop,memwrite,memtoreg,alusrc,j_sel,npc_sel,rd_dst,flag_sel,jr_sel,jal_sel,addi_sel,slt_sel);
    input [4:0]rt;
    input [5:0]funct;
    input [5:0]opcode;
    output reg regwr,memwrite,memtoreg,alusrc,j_sel,npc_sel,rd_dst,flag_sel;
    output reg [1:0]aluop,extop;
    output jr_sel,jal_sel,addi_sel,slt_sel;
    assign jal_sel=(opcode==6'b000011);
    assign jr_sel=(opcode==6'b000000&&funct==6'b001000);
    assign addi_sel=(opcode==6'b001000);
    assign slt_sel=(opcode==6'b000000&&funct==6'b101010);
    always @ (funct or opcode) begin
        if(opcode==6'b001101)//ori
        begin
            j_sel=0;
            aluop=2'b10;//or
            extop=2'b00;
            regwr=1;
            memwrite=0;
            alusrc=1;
            memtoreg=0;
            rd_dst=0;
            npc_sel=0;
            flag_sel=0;
        end
        if(opcode==6'b000000&&funct==6'b100001)//addu
        begin
            j_sel=0;
            aluop=2'b00;//add
            extop=2'b00;
            regwr=1;
            memwrite=0;
            alusrc=0;
            memtoreg=0;
            rd_dst=1;
            npc_sel=0;
            flag_sel=0;
        end
        if(opcode==6'b000000&&funct==6'b100011)//subu
        begin
            j_sel=0;
            aluop=2'b01;//sub
            extop=2'b00;
            regwr=1;
            memwrite=0;
            alusrc=0;
            memtoreg=0;
            rd_dst=1;
            npc_sel=0;
            flag_sel=0;
        end
        if(opcode==6'b100011)//lw
        begin
            j_sel=0;
            aluop=2'b00;//add
            extop=2'b01;
            regwr=1;
            memwrite=0;
            alusrc=1;
            memtoreg=1;
            rd_dst=0;
            npc_sel=0;
            flag_sel=0;
        end
        if(opcode==6'b101011)//sw
        begin
            j_sel=0;
            aluop=2'b00;//add
            extop=2'b01;
            regwr=0;
            memwrite=1;
            alusrc=1;
            memtoreg=0;
            rd_dst=0;
            npc_sel=0;
            flag_sel=0;
        end
        if(opcode==6'b000100)//beq
        begin
            j_sel=0;
            aluop=2'b01;//sub
            extop=2'b00;
            regwr=0;
            memwrite=0;
            alusrc=0;
            memtoreg=0;
            rd_dst=0;
            npc_sel=1;
            flag_sel=0;
        end
        if(opcode==6'b001111)//lui
        begin
            j_sel=0;
            aluop=2'b00;//add
            extop=2'b10;
            regwr=1;
            memwrite=0;
            alusrc=1;
            memtoreg=0;
            rd_dst=0;
            npc_sel=0;
            flag_sel=0;
        end
        if(opcode==6'b000010)//j
        begin
            j_sel=1;
            aluop=2'b00;//add
            extop=2'b00;
            regwr=0;
            memwrite=0;
            alusrc=0;
            memtoreg=0;
            rd_dst=0;
            npc_sel=1;
            flag_sel=0;
        end
        if(opcode==6'b001000)//addi
        begin
            j_sel=0;
            aluop=2'b00;//add
            extop=2'b01;
            regwr=1;
            memwrite=0;
            alusrc=1;
            memtoreg=0;
            rd_dst=0;
            npc_sel=0;
            flag_sel=1;
        end
        if(opcode==6'b001001)//addiu
        begin
            j_sel=0;
            aluop=2'b00;//add
            extop=2'b01;
            regwr=1;
            memwrite=0;
            alusrc=1;
            memtoreg=0;
            rd_dst=0;
            npc_sel=0;
            flag_sel=0;
        end
        if(opcode==6'b000000&&funct==6'b101010)//slt
        begin
            j_sel=0;
            aluop=2'b01;//sub
            extop=2'b00;
            regwr=1;
            memwrite=0;
            alusrc=0;
            memtoreg=0;
            rd_dst=1;
            npc_sel=0;
            flag_sel=0;
        end
        if(opcode==6'b000011)//jar;
        begin
            j_sel=1;
            aluop=2'b00;//add
            extop=2'b00;
            regwr=1;
            memwrite=0;
            alusrc=0;
            memtoreg=0;
            rd_dst=0;
            npc_sel=0;
            flag_sel=0;
        end
        if(opcode==6'b000000&&funct==6'b001000)//jr
        begin
            j_sel=1;
            aluop=2'b00;//add
            extop=2'b00;
            regwr=0;
            memwrite=0;
            alusrc=0;
            memtoreg=0;
            rd_dst=0;
            npc_sel=0;
            flag_sel=0;
        end
    end
endmodule

single_cycle_MIPS/src/alu.v
module alu(input [31:0]a, input [31:0]b, input [1:0]aluop, output [31:0] aluout, output zero, output flag,input slt_sel,input flagsel);
    reg [31:0]temp;

    assign aluout=(slt_sel)?temp[31]:temp[31:0];
    
    assign zero=(aluout==0)?1:0;
 
    assign flag = (flagsel) ? ((a[31] == 0 && b[31] == 0 && temp[31] == 1) || (a[31] == 1 && b[31] == 1 && temp[31] == 0)) : 0;

    always@(a or b or aluop) begin
        case(aluop)
            2'b00:
                temp<=a+b;
            2'b01:
                temp<=a-b;
            2'b10:
                temp<=a|b;
            2'b11:
                temp<=0;
            default:
                temp<=0;
        endcase
    end

endmodule

single_cycle_MIPS/src/mips.v
`include "src/alu.v"
`include "src/controller.v"
`include "src/controllersel.v"
`include "src/gpr.v"
`include "src/ifu.v"
`include "src/im.v"
`include "src/ext32.v"
`include "src/dm.v"
module mips(clk, rst) ;
    input           clk ;   
    input           rst ;  
    wire [9:0]addrdm;
    wire [31:0]a,b,alu_b,aluout,dmout,pc,dout,din,jr;
    wire [1:0]aluop,extop;
    wire zero,flag,regwr,memwrite,memtoreg,alusrc,j_sel,npc_sel,l,rd_dst,flag_sel,jr_sel,jal_sel,addi_sel,slt_sel,flagsel;
    wire [5:0]opcode,funct;
    wire [4:0]rs,rt,rd,rdtmp;
    wire [15:0]imm;

    assign addrdm=aluout[9:0];
    assign rd=(rd_dst)?rdtmp:rt;
    assign flagsel=addi_sel;
    assign din=(memtoreg)?dmout:aluout;

    alu alu1(a,alu_b,aluop,aluout,zero,flag,slt_sel,flagsel);
    controllersel sel(rt,opcode,funct,aluop,regwr,extop,memwrite,memtoreg,alusrc,j_sel,npc_sel,rd_dst,flag_sel,jr_sel,jal_sel,addi_sel,slt_sel);
    dm_1k dm1(addrdm, b, memwrite, clk, dmout);
    gpr gpr1(rs,rt,rd,din,flag_sel,flag,pc,clk,rst,jal_sel,jr_sel,regwr,a,b,addi_sel);
    ifu ifu1(clk,rst,j_sel,jr_sel,npc_sel,zero,aluout,pc,dout);
    controller ctrl1(dout,rdtmp,rs,rt,funct,opcode,imm);
    ext32 ext(imm,extop,b,alusrc,alu_b);

endmodule

single_cycle_MIPS/tests/test.v
`timescale 1ns/1ps
module test;
    reg clk=0,rst=0;
    integer i;

    mips my_mips(clk,rst);

    initial begin
        clk=0;
        rst=0;
        #5
         rst=1;
        #15
         rst=0;

        $readmemh("tests/p1-test.txt",my_mips.ifu1.im); // load into im
        $dumpfile("build/test.vcd");
        $dumpvars(0, test);

        #2000
         $display("Register values:");
        for(i=0;i<32;i=i+1) begin
            $display("t[%0d] = %h " , i, my_mips.gpr1.t[i]);
        end
        $finish;
    end
    always begin
        #10 clk=~clk;
    end
endmodule

single_cycle_MIPS/build/test.vcd
$date
	Mon Jul 01 13:52:02 2024
$end
$version
	Icarus Verilog
$end
$timescale
	1ps
$end
$scope module test $end
$var reg 1 ! clk $end
$var reg 1 " rst $end
$var integer 32 # i [31:0] $end
$scope module my_mips $end
$var wire 1 ! clk $end
$var wire 1 $ flagsel $end
$var wire 1 " rst $end
$var wire 1 % zero $end
$var wire 1 & slt_sel $end
$var wire 5 ' rt [4:0] $end
$var wire 5 ( rs [4:0] $end
$var wire 1 ) regwr $end
$var wire 5 * rdtmp [4:0] $end
$var wire 1 + rd_dst $end
$var wire 5 , rd [4:0] $end
$var wire 32 - pc [31:0] $end
$var wire 6 . opcode [5:0] $end
$var wire 1 / npc_sel $end
$var wire 1 0 memwrite $end
$var wire 1 1 memtoreg $end
$var wire 1 2 jr_sel $end
$var wire 1 3 jal_sel $end
$var wire 1 4 j_sel $end
$var wire 16 5 imm [15:0] $end
$var wire 6 6 funct [5:0] $end
$var wire 1 7 flag_sel $end
$var wire 1 8 flag $end
$var wire 2 9 extop [1:0] $end
$var wire 32 : dout [31:0] $end
$var wire 32 ; dmout [31:0] $end
$var wire 32 < din [31:0] $end
$var wire 32 = b [31:0] $end
$var wire 1 > alusrc $end
$var wire 32 ? aluout [31:0] $end
$var wire 2 @ aluop [1:0] $end
$var wire 32 A alu_b [31:0] $end
$var wire 10 B addrdm [9:0] $end
$var wire 1 C addi_sel $end
$var wire 32 D a [31:0] $end
$scope module alu1 $end
$var wire 1 $ flagsel $end
$var wire 1 % zero $end
$var wire 1 & slt_sel $end
$var wire 1 8 flag $end
$var wire 32 E b [31:0] $end
$var wire 32 F aluout [31:0] $end
$var wire 2 G aluop [1:0] $end
$var wire 32 H a [31:0] $end
$var reg 32 I temp [31:0] $end
$upscope $end
$scope module ctrl1 $end
$var wire 5 J rt [4:0] $end
$var wire 5 K rs [4:0] $end
$var wire 5 L rd [4:0] $end
$var wire 6 M opcode [5:0] $end
$var wire 16 N imm [15:0] $end
$var wire 6 O funct [5:0] $end
$var wire 32 P din [31:0] $end
$upscope $end
$scope module dm1 $end
$var wire 10 Q addr [9:0] $end
$var wire 1 ! clk $end
$var wire 1 0 we $end
$var wire 32 R dout [31:0] $end
$var wire 32 S din [31:0] $end
$var integer 32 T i [31:0] $end
$upscope $end
$scope module ext $end
$var wire 16 U imm [15:0] $end
$var wire 2 V extop [1:0] $end
$var wire 1 > b_sel $end
$var wire 32 W b [31:0] $end
$var wire 32 X alu_b [31:0] $end
$var reg 32 Y imm32 [31:0] $end
$upscope $end
$scope module gpr1 $end
$var wire 32 Z b [31:0] $end
$var wire 1 ! clk $end
$var wire 32 [ din [31:0] $end
$var wire 1 8 flag $end
$var wire 5 \ rd [4:0] $end
$var wire 5 ] rs [4:0] $end
$var wire 1 " rst $end
$var wire 5 ^ rt [4:0] $end
$var wire 1 ) regwr $end
$var wire 32 _ pc [31:0] $end
$var wire 1 2 jr_sel $end
$var wire 1 3 jal_sel $end
$var wire 1 7 flag_sel $end
$var wire 1 C addi_sel $end
$var wire 32 ` a [31:0] $end
$var integer 32 a i [31:0] $end
$upscope $end
$scope module ifu1 $end
$var wire 1 ! clk $end
$var wire 32 b jr [31:0] $end
$var wire 1 " reset $end
$var wire 1 % zero $end
$var wire 32 c temp [31:0] $end
$var wire 32 d t3 [31:0] $end
$var wire 32 e t2 [31:0] $end
$var wire 32 f t1 [31:0] $end
$var wire 32 g t0 [31:0] $end
$var wire 1 / npc_sel $end
$var wire 32 h npc [31:0] $end
$var wire 1 2 jr_sel $end
$var wire 1 4 j_sel $end
$var wire 32 i j [31:0] $end
$var wire 16 j imm [15:0] $end
$var wire 32 k extout [31:0] $end
$var wire 32 l dout [31:0] $end
$var reg 32 m pc [31:0] $end
$upscope $end
$scope module sel $end
$var wire 6 n funct [5:0] $end
$var wire 1 2 jr_sel $end
$var wire 6 o opcode [5:0] $end
$var wire 5 p rt [4:0] $end
$var wire 1 & slt_sel $end
$var wire 1 3 jal_sel $end
$var wire 1 C addi_sel $end
$var reg 2 q aluop [1:0] $end
$var reg 1 > alusrc $end
$var reg 2 r extop [1:0] $end
$var reg 1 7 flag_sel $end
$var reg 1 4 j_sel $end
$var reg 1 1 memtoreg $end
$var reg 1 0 memwrite $end
$var reg 1 / npc_sel $end
$var reg 1 + rd_dst $end
$var reg 1 ) regwr $end
$upscope $end
$upscope $end
$upscope $end
$enddefinitions $end
$comment Show the parameter values. $end
$dumpall
$end
#20000
$dumpvars
b0 r
b10 q
b10000 p
b1101 o
b1 n
b11000000000000 m
b110100000100000000000000000001 l
b100 k
b1 j
b10000000000000000000100 i
b11000000000100 h
b11000000000100 g
b11000000001000 f
b11000000000100 e
b11000000000100 d
b1 c
b1 b
b100000 a
b0 `
b11000000000000 _
b10000 ^
b0 ]
b10000 \
b1 [
b0 Z
b1 Y
b1 X
b0 W
b0 V
b1 U
b10000000000 T
b0 S
b0 R
b1 Q
b110100000100000000000000000001 P
b1 O
b1 N
b1101 M
b0 L
b0 K
b10000 J
b1 I
b0 H
b10 G
b1 F
b1 E
b0 D
0C
b1 B
b1 A
b10 @
b1 ?
1>
b0 =
b1 <
b0 ;
b110100000100000000000000000001 :
b0 9
08
07
b1 6
b1 5
04
03
02
01
00
0/
b1101 .
b11000000000000 -
b10000 ,
0+
b0 *
1)
b0 (
b10000 '
0&
0%
0$
bx #
0"
0!
$end
#30000
b11 <
b11 [
b11 B
b11 Q
b11 ?
b11 F
b11 b
b11 I
b11 A
b11 E
b11 X
b10001 ,
b10001 \
b1100 k
b11 Y
b11000000001000 h
b10001 '
b10001 J
b10001 ^
b10001 p
b10001000000000000001100 i
b11 c
b11 j
b11 5
b11 N
b11 U
b11 6
b11 O
b11 n
b11000000001000 d
b110100000100010000000000000011 :
b110100000100010000000000000011 P
b110100000100010000000000000011 l
b11000000001000 e
b0 =
b0 S
b0 W
b0 Z
b11000000010100 f
b11000000001000 g
b11000000000100 -
b11000000000100 _
b11000000000100 m
1!
#40000
0!
#50000
b1 <
b1 [
b1 B
b1 Q
b1 ?
b1 F
b1 b
b1 I
b1 A
b1 E
b1 X
b1000 ,
b1000 \
b100 k
b1 Y
b11000000001100 h
b1000 '
b1000 J
b1000 ^
b1000 p
b1000000000000000000100 i
b1 c
b1 j
b1 5
b1 N
b1 U
b1 6
b1 O
b1 n
b11000000001100 d
b110100000010000000000000000001 :
b110100000010000000000000000001 P
b110100000010000000000000000001 l
b11000000001100 e
b11000000010000 f
b11000000001100 g
b11000000001000 -
b11000000001000 _
b11000000001000 m
b0 =
b0 S
b0 W
b0 Z
1!
#60000
0!
#70000
b1010101110101011 <
b1010101110101011 [
b1110101011 B
b1110101011 Q
b1010101110101011 ?
b1010101110101011 F
b1010101110101011 b
b1010101110101011 I
b1010101110101011 A
b1010101110101011 E
b1010101110101011 X
b1100 ,
b1100 \
b11111111111111101010111010101100 k
b1010101110101011 Y
b11000000010000 h
b1100 '
b1100 J
b1100 ^
b1100 p
b10101 *
b10101 L
b1100101010111010101100 i
b11111111111111111010101110101011 c
b1010101110101011 j
b1010101110101011 5
b1010101110101011 N
b1010101110101011 U
b101011 6
b101011 O
b101011 n
b11000000010000 d
b110100000011001010101110101011 :
b110100000011001010101110101011 P
b110100000011001010101110101011 l
b11000000010000 e
b0 =
b0 S
b0 W
b0 Z
b11111111111111101101111010111100 f
b11000000010000 g
b11000000001100 -
b11000000001100 _
b11000000001100 m
1!
#80000
0!
#90000
b10100000000000000000 <
b10100000000000000000 [
b0 B
b0 Q
b10100000000000000000 ?
b10100000000000000000 F
b10100000000000000000 b
b10100000000000000000 I
b10100000000000000000 A
b10100000000000000000 E
b10100000000000000000 X
b1101 ,
b1101 \
b101000 k
b10100000000000000000 Y
b10 9
b10 V
b10 r
b0 @
b0 G
b0 q
b11000000010100 h
b1111 .
b1111 M
b1111 o
b1101 '
b1101 J
b1101 ^
b1101 p
b0 *
b0 L
b1101000000000000101000 i
b1010 c
b1010 j
b1010 5
b1010 N
b1010 U
b1010 6
b1010 O
b1010 n
b11000000010100 d
b111100000011010000000000001010 :
b111100000011010000000000001010 P
b111100000011010000000000001010 l
b11000000010100 e
b11000000111100 f
b11000000010100 g
b11000000010000 -
b11000000010000 _
b11000000010000 m
b0 =
b0 S
b0 W
b0 Z
1!
#100000
0!
#110000
b1 <
b1 [
b1 B
b1 Q
b1 ?
b1 F
b1 b
b1 I
b1 A
b1 E
b1 X
b100 ,
b100 \
b1000000010000100 k
b10000000100001 Y
1+
0>
b0 9
b0 V
b0 r
b11000000011000 h
b0 .
b0 M
b0 o
b10000 '
b10000 J
b10000 ^
b10000 p
b100 *
b100 L
b10000001000000010000100 i
b10000000100001 c
b10000000100001 j
b10000000100001 5
b10000000100001 N
b10000000100001 U
b100001 6
b100001 O
b100001 n
b11000000011000 d
b100000010000000100001 :
b100000010000000100001 P
b100000010000000100001 l
b11000000011000 e
b1 =
b1 S
b1 W
b1 Z
b1011000010011100 f
b11000000011000 g
b11000000010100 -
b11000000010100 _
b11000000010100 m
1!
#120000
0!
#130000
b1010000010000100 k
b10100000100001 Y
b101 ,
b101 \
b11000000011100 h
b1000 '
b1000 J
b1000 ^
b1000 p
b1000001010000010000100 i
b10100000100001 c
b10100000100001 j
b10100000100001 5
b10100000100001 N
b10100000100001 U
b101 *
b101 L
b11000000011100 d
b10000010100000100001 :
b10000010100000100001 P
b10000010100000100001 l
b11000000011100 e
b1101000010100000 f
b11000000011100 g
b11000000011000 -
b11000000011000 _
b11000000011000 m
1!
#140000
0!
#150000
1%
b0 <
b0 [
b0 B
b0 Q
b0 ?
b0 F
b0 b
b0 I
b0 A
b0 E
b0 X
b0 ,
b0 \
b11000011001000 k
b110000110010 Y
0+
14
b11000011001000 h
13
b11 .
b11 M
b11 o
b0 =
b0 S
b0 W
b0 Z
b0 '
b0 J
b0 ^
b0 p
b1 *
b1 L
b11000011001000 i
b110000110010 c
b110000110010 j
b110000110010 5
b110000110010 N
b110000110010 U
b110010 6
b110010 O
b110010 n
b11000011001000 d
b1100000000000000110000110010 :
b1100000000000000110000110010 P
b1100000000000000110000110010 l
b11000000100000 e
b110000011101000 f
b11000000100000 g
b11000000011100 -
b11000000011100 _
b11000000011100 m
1!
#160000
0!
#170000
0%
b10 <
b10 [
b10 B
b10 Q
b10 ?
b10 F
b10 b
b10 I
b11000011001100 h
b1 A
b1 E
b1 X
b10 ,
b10 \
b1 D
b1 H
b1 `
b11000011001100 d
b100000010000100 k
b1000000100001 Y
1+
04
03
b0 .
b0 M
b0 o
b1 =
b1 S
b1 W
b1 Z
b101 '
b101 J
b101 ^
b101 p
b100 (
b100 K
b100 ]
b10 *
b10 L
b10000101000100000010000100 i
b1000000100001 c
b1000000100001 j
b1000000100001 5
b1000000100001 N
b1000000100001 U
b100001 6
b100001 O
b100001 n
b100001010001000000100001 :
b100001010001000000100001 P
b100001010001000000100001 l
b11000011001100 e
b111000101010000 f
b11000011001100 g
b11000011001000 -
b11000011001000 _
b11000011001000 m
1!
#180000
0!
#190000
b1011110111011111 <
b1011110111011111 [
b111011111 B
b111011111 Q
b1011110111011111 ?
b1011110111011111 F
b1011110111011111 b
b1011110111011111 I
b0 ,
b0 \
b1010101110101011 D
b1010101110101011 H
b1010101110101011 `
b1001000110100 A
b1001000110100 E
b1001000110100 X
b100100011010000 k
b1001000110100 Y
17
0+
1>
b1 9
b1 V
b1 r
b11000011010000 h
b1100 (
b1100 K
b1100 ]
1$
1C
b1000 .
b1000 M
b1000 o
b0 =
b0 S
b0 W
b0 Z
b0 '
b0 J
b0 ^
b0 p
b110000000000100100011010000 i
b1001000110100 c
b1001000110100 j
b1001000110100 5
b1001000110100 N
b1001000110100 U
b110100 6
b110100 O
b110100 n
b11000011010000 d
b100001100000000001001000110100 :
b100001100000000001001000110100 P
b100001100000000001001000110100 l
b11000011010000 e
b111100110100000 f
b11000011010000 g
b11000011001100 -
b11000011001100 _
b11000011001100 m
1!
#200000
0!
#210000
b11000000100000 <
b11000000100000 [
b100000 B
b100000 Q
b11000000100000 ?
b11000000100000 F
b11000000100000 b
b11000000100000 I
b0 A
b0 E
b0 X
b11000000100000 D
b11000000100000 H
b11000000100000 `
b100000 k
b1000 Y
12
07
0>
0)
b0 9
b0 V
b0 r
14
b11000000100000 h
0$
0C
b0 .
b0 M
b0 o
b11111 (
b11111 K
b11111 ]
b0 *
b0 L
b1111100000000000000000100000 i
b1000 c
b1000 j
b1000 5
b1000 N
b1000 U
b1000 6
b1000 O
b1000 n
b1111100000000000000000100000 d
b11111000000000000000001000 :
b11111000000000000000001000 P
b11111000000000000000001000 l
b11000011010100 e
b11000011110100 f
b11000011010100 g
b11000011010000 -
b11000011010000 _
b11000011010000 m
1!
#220000
0!
#230000
b10 <
b10 [
b10 B
b10 Q
b10 ?
b10 F
b10 b
b10 I
b11000000100100 h
b0 D
b0 H
b0 `
b10 A
b10 E
b10 X
b10000 ,
b10000 \
b11000000100100 d
b11111111111111100000000010000100 k
b1000000000100001 Y
02
1+
1)
04
b10 =
b10 S
b10 W
b10 Z
b10 '
b10 J
b10 ^
b10 p
b0 (
b0 K
b0 ]
b10000 *
b10000 L
b10100000000010000100 i
b11111111111111111000000000100001 c
b1000000000100001 j
b1000000000100001 5
b1000000000100001 N
b1000000000100001 U
b100001 6
b100001 O
b100001 n
b101000000000100001 :
b101000000000100001 P
b101000000000100001 l
b11000000100100 e
b11111111111111100011000010101000 f
b11000000100100 g
b11000000100000 -
b11000000100000 _
b11000000100000 m
1!
#240000
0!
#250000
b1 A
b1 E
b1 X
b11 D
b11 H
b11 `
b10001 ,
b10001 \
b11111111111111100010000010001100 k
b1000100000100011 Y
b1 @
b1 G
b1 q
b11000000101000 h
b1 =
b1 S
b1 W
b1 Z
b1000 '
b1000 J
b1000 ^
b1000 p
b10001 (
b10001 K
b10001 ]
b10001 *
b10001 L
b1000101000100010000010001100 i
b11111111111111111000100000100011 c
b1000100000100011 j
b1000100000100011 5
b1000100000100011 N
b1000100000100011 U
b100011 6
b100011 O
b100011 n
b11000000101000 d
b10001010001000100000100011 :
b10001010001000100000100011 P
b10001010001000100000100011 l
b11000000101000 e
b11111111111111100101000010110100 f
b11000000101000 g
b11000000100100 -
b11000000100100 _
b11000000100100 m
1!
#260000
0!
#270000
1%
b0 <
b0 [
b0 B
b0 Q
b0 ?
b0 F
b0 b
b0 I
b10 A
b10 E
b10 X
b11111111111111111111111111101000 k
b1111111111111010 Y
1/
0+
0)
b11000000010100 h
b100 .
b100 M
b100 o
b10 =
b10 S
b10 W
b10 Z
b10001 '
b10001 J
b10001 ^
b10001 p
b10000 (
b10000 K
b10000 ]
b11111 *
b11111 L
b1000010001111111111111101000 i
b11111111111111111111111111111010 c
b1111111111111010 j
b1111111111111010 5
b1111111111111010 N
b1111111111111010 U
b111010 6
b111010 O
b111010 n
b11000000010100 d
b10 D
b10 H
b10 `
b10010000100011111111111111010 :
b10010000100011111111111111010 P
b10010000100011111111111111010 l
b11000000010100 e
b11000000010100 f
b11000000101100 g
b11000000101000 -
b11000000101000 _
b11000000101000 m
1!
#280000
0!
#290000
0%
b10 <
b10 [
b10 B
b10 Q
b10 ?
b10 F
b10 b
b10 I
b0 D
b0 H
b0 `
b100 ,
b100 \
b1000000010000100 k
b10000000100001 Y
0/
1+
1)
b0 @
b0 G
b0 q
b11000000011000 h
b0 (
b0 K
b0 ]
b0 .
b0 M
b0 o
b10000 '
b10000 J
b10000 ^
b10000 p
b100 *
b100 L
b10000001000000010000100 i
b10000000100001 c
b10000000100001 j
b10000000100001 5
b10000000100001 N
b10000000100001 U
b100001 6
b100001 O
b100001 n
b11000000011000 d
b100000010000000100001 :
b100000010000000100001 P
b100000010000000100001 l
b11000000011000 e
b1011000010011100 f
b11000000011000 g
b11000000010100 -
b11000000010100 _
b11000000010100 m
1!
#300000
0!
#310000
b1 <
b1 [
b1 B
b1 Q
b1 ?
b1 F
b1 b
b1 I
b1 A
b1 E
b1 X
b1010000010000100 k
b10100000100001 Y
b101 ,
b101 \
b11000000011100 h
b1 =
b1 S
b1 W
b1 Z
b1000 '
b1000 J
b1000 ^
b1000 p
b1000001010000010000100 i
b10100000100001 c
b10100000100001 j
b10100000100001 5
b10100000100001 N
b10100000100001 U
b101 *
b101 L
b11000000011100 d
b10000010100000100001 :
b10000010100000100001 P
b10000010100000100001 l
b11000000011100 e
b1101000010100000 f
b11000000011100 g
b11000000011000 -
b11000000011000 _
b11000000011000 m
1!
#320000
0!
#330000
1%
b0 <
b0 [
b0 B
b0 Q
b0 ?
b0 F
b0 b
b0 I
b0 A
b0 E
b0 X
b0 ,
b0 \
b11000011001000 k
b110000110010 Y
0+
14
b11000011001000 h
13
b11 .
b11 M
b11 o
b0 =
b0 S
b0 W
b0 Z
b0 '
b0 J
b0 ^
b0 p
b1 *
b1 L
b11000011001000 i
b110000110010 c
b110000110010 j
b110000110010 5
b110000110010 N
b110000110010 U
b110010 6
b110010 O
b110010 n
b11000011001000 d
b1100000000000000110000110010 :
b1100000000000000110000110010 P
b1100000000000000110000110010 l
b11000000100000 e
b110000011101000 f
b11000000100000 g
b11000000011100 -
b11000000011100 _
b11000000011100 m
1!
#340000
0!
#350000
0%
b11 <
b11 [
b11 B
b11 Q
b11 ?
b11 F
b11 b
b11 I
b11000011001100 h
b1 A
b1 E
b1 X
b10 ,
b10 \
b10 D
b10 H
b10 `
b11000011001100 d
b100000010000100 k
b1000000100001 Y
1+
04
03
b0 .
b0 M
b0 o
b1 =
b1 S
b1 W
b1 Z
b101 '
b101 J
b101 ^
b101 p
b100 (
b100 K
b100 ]
b10 *
b10 L
b10000101000100000010000100 i
b1000000100001 c
b1000000100001 j
b1000000100001 5
b1000000100001 N
b1000000100001 U
b100001 6
b100001 O
b100001 n
b100001010001000000100001 :
b100001010001000000100001 P
b100001010001000000100001 l
b11000011001100 e
b111000101010000 f
b11000011001100 g
b11000011001000 -
b11000011001000 _
b11000011001000 m
1!
#360000
0!
#370000
b1011110111011111 <
b1011110111011111 [
b111011111 B
b111011111 Q
b1011110111011111 ?
b1011110111011111 F
b1011110111011111 b
b1011110111011111 I
b0 ,
b0 \
b1010101110101011 D
b1010101110101011 H
b1010101110101011 `
b1001000110100 A
b1001000110100 E
b1001000110100 X
b100100011010000 k
b1001000110100 Y
17
0+
1>
b1 9
b1 V
b1 r
b11000011010000 h
b1100 (
b1100 K
b1100 ]
1$
1C
b1000 .
b1000 M
b1000 o
b0 =
b0 S
b0 W
b0 Z
b0 '
b0 J
b0 ^
b0 p
b110000000000100100011010000 i
b1001000110100 c
b1001000110100 j
b1001000110100 5
b1001000110100 N
b1001000110100 U
b110100 6
b110100 O
b110100 n
b11000011010000 d
b100001100000000001001000110100 :
b100001100000000001001000110100 P
b100001100000000001001000110100 l
b11000011010000 e
b111100110100000 f
b11000011010000 g
b11000011001100 -
b11000011001100 _
b11000011001100 m
1!
#380000
0!
